pip_middleware_fluig/__init__.py
pip_middleware_fluig/domain/__init__.py
pip_middleware_fluig/domain/ecm_services.py
pip_middleware_fluig/domain/exceptions.py
pip_middleware_fluig/interface/__init__.py
pip_middleware_fluig/interface/ecm_dataset.py
pip_middleware_fluig/repositories/__init__.py
pip_middleware_fluig/repositories/soap.py
pip_middleware_fluig/services/__init__.py
pip_middleware_fluig/services/ecm_fluig_service.py
pip_middleware_fluig/setting.py
pip_middleware_fluig/tests/__init__.py
pip_middleware_fluig/utils/__init__.py
pip_middleware_fluig/utils/common_functions.py
pip_middleware_fluig-0.1.9.dist-info/WHEEL
pip_middleware_fluig-0.1.9.dist-info/METADATA
pip_middleware_fluig-0.1.9.dist-info/RECORD
