Metadata-Version: 2.1
Name: pip-middleware-fluig
Version: 0.1.9
Summary: middleware service fluig plataform
Author: Rodrigo Becker
Author-email: rodrigo.beckermore@gmail.com
Requires-Python: >=3.9,<4.0
Classifier: Programming Language :: Python :: 3
Classifier: Programming Language :: Python :: 3.10
Classifier: Programming Language :: Python :: 3.9
Requires-Dist: black (>=22.1.0,<23.0.0)
Requires-Dist: httpx (>=0.22.0,<0.23.0)
Requires-Dist: ipython (>=8.2.0,<9.0.0)
Requires-Dist: pydantic (>=1.9.0,<2.0.0)
Requires-Dist: pytest (>=7.1.1,<8.0.0)
Requires-Dist: safety (>=1.10.3,<2.0.0)
Requires-Dist: twine (>=3.8.0,<4.0.0)
Requires-Dist: zeep (>=4.1.0,<5.0.0)
